{
  "subtitle": "How to cook food safely ", 
  "description": "Siga esta guia", 
  "language": "por_PT", 
  "title": "Cuidados importantes na hora de cozinhar", 
  "primary_category": "ac28a6b0b1bf4555a431fa585788d1eb", 
  "created_at": "2015-05-28T11:57:38+00:00", 
  "featured_in_category": false, 
  "modified_at": "2015-12-11T14:33:58.615031+00:00", 
  "_version": {
    "package_version": "1.2.0", 
    "language_version": "2.7.6", 
    "language": "python", 
    "language_version_string": "2.7.6 (default, Mar 22 2014, 23:03:41) \n[GCC 4.8.2]", 
    "package": "elastic-git"
  }, 
  "linked_pages": [
    "f9ffe33c7fbc463ea07440fbbd57e206", 
    "870ba0686f0c43ebbd4cbca8b8cff025"
  ], 
  "id": null, 
  "content": "Criado pelo BabyCenter\r\n\r\n\r\nComidas estragadas ou passadas podem deixar voc\u00ea doente. Procure preparar comida nova todos os dias. Mantenha limpo o lugar onde voc\u00ea cozinha e come, e guarde a comida em um local fresco e seco. \r\n\r\n\u2022\tCozinhe bem a carne e o frango, at\u00e9 que n\u00e3o fique nenhum peda\u00e7o rosado ou avermelhado.  \r\n\r\n\u2022\tCozinhe os ovos at\u00e9 ficarem firmes. Ferva o leite para matar germes que causam doen\u00e7as.  \r\n\r\n\u2022\tQuando comprar comida pronta em bancas ou carrinhos de rua, escolha os lugares mais limpos. Escolha o local com maior movimento, assim voc\u00ea ter\u00e1 certeza que a comida n\u00e3o ficou parada muito tempo e que outras pessoas comeram sem problemas. \r\n\r\n\u2022\tLave as m\u00e3os com \u00e1gua e sab\u00e3o antes de preparar alimentos, e depois de ir ao banheiro e lidar com animais.  \r\n\r\n\u2022\tLave toda a lou\u00e7a e o local onde voc\u00ea cozinhou com \u00e1gua e sab\u00e3o para retirar qualquer sobra de alimentos.   \r\n\r\nSe voc\u00ea tiver alguma ferida ou corte na m\u00e3o, mantenha-o limpo e coberto com um pano limpo. \r\n\r\nMantenha os animais afastados do lugar onde voc\u00ea cozinha.  Os animais podem espalhar germes que deixam voc\u00ea doente. \r\n", 
  "source": "4090e50a388c41cbabf952377aeec1ec", 
  "featured": false, 
  "author_tags": [], 
  "image": null, 
  "published": null, 
  "position": 64, 
  "image_host": "http://thumbor.unicore.io", 
  "slug": "cuidados-importantes-na-hora-de-cozinhar", 
  "uuid": "bac5a9d8aa4f42268e843e4b555ff648"
}