{
  "subtitle": "POR 3 months old", 
  "description": "Ele adora brincar", 
  "language": "por_PT", 
  "title": "Seu beb\u00ea de 3 meses", 
  "primary_category": "9bd14ebe21394b81bc2a1bd8a850ba85", 
  "created_at": "2015-05-13T10:45:04+00:00", 
  "featured_in_category": false, 
  "modified_at": "2015-08-11T12:34:54.434970+00:00", 
  "_version": {
    "package_version": "1.0.2", 
    "language_version": "2.7.6", 
    "language": "python", 
    "language_version_string": "2.7.6 (default, Mar 22 2014, 23:03:41) \n[GCC 4.8.2]", 
    "package": "elastic-git"
  }, 
  "linked_pages": [
    "3fe5c8206c8b4e28b55896913a4391dc", 
    "55ab1b75790b49598dfc60368a3f178d"
  ], 
  "id": null, 
  "content": "Criado pelo BabyCenter\r\n\r\nO corpo do seu beb\u00ea agora \u00e9 mais flex\u00edvel. Ele se diverte abrindo e fechando as m\u00e3os ou batendo palminhas. \r\n\r\n O senso de humor do seu nen\u00e9m tamb\u00e9m est\u00e1 se desenvolvendo. \u00c9 s\u00f3 voc\u00ea fazer c\u00f3cegas ou dar um beijinho barulhento na sua barriguinha para ele cair na gargalhada. \r\n\r\n Desde o momento em que nasce, seu beb\u00ea adora ser tocado e acariciado. Isso \u00e9 importante para seu crescimento e desenvolvimento. Mais ou menos por volta desta \u00e9poca, seu beb\u00ea tamb\u00e9m vai achar interessante tocar e sentir texturas diferentes. \r\n\r\n\u00c0 medida que ele vai compreendendo melhor o mundo que o rodeia, brincar ajuda o c\u00e9rebro do beb\u00ea a crescer. O c\u00e9rebro do beb\u00ea vai se desenvolvendo e ele vai ficando cada vez mais curioso. Ele pode gostar de brincar com brinquedos pequenos que ele possa segurar e sacudir. Brincando ele aprende sobre as cores, formas e tamanhos. Ele tamb\u00e9m aprende ao escutar os sons que o brinquedo faz e sentir se o brinquedo \u00e9 duro ou macio. \r\n\r\nNesta idade, quando est\u00e1 de barriga para baixo, talvez ele j\u00e1 possa levantar a cabe\u00e7a e os ombros, usando os bra\u00e7os de apoio. Pode ser at\u00e9 que ele consiga se virar, de frente para as costas. Incentive-o sacudindo um brinquedo do lado que ele costuma virar. Bata palmas e sorria quando ele conseguir!  \r\n\r\n", 
  "source": "43386657778548b08b8bc7089e3dc8e5", 
  "featured": false, 
  "author_tags": [], 
  "image": null, 
  "published": null, 
  "position": 120, 
  "image_host": "http://thumbor.unicore.io", 
  "slug": "por-3-months-old", 
  "uuid": "c8f8f0ab19aa4c9ba756997740367623"
}